README.rst
setup.py
pysentosa/__init__.py
pysentosa/config.py
pysentosa/demo.py
pysentosa/historicaldata.py
pysentosa/merlion.py
pysentosa/order.py
pysentosa/sentosa_.so
pysentosa/ticktype.py
pysentosa/tradeinfo.py
pysentosa/volatility.py
pysentosa.egg-info/PKG-INFO
pysentosa.egg-info/SOURCES.txt
pysentosa.egg-info/dependency_links.txt
pysentosa.egg-info/top_level.txt
tests/__init__.py
tests/test_pysentosa.py
tests/test_volatility.py