Metadata-Version: 1.0
Name: pysentosa
Version: 0.1.32
Summary: pysentosa - Python API for sentosa trading system
Home-page: http://www.quant365.com
Author: Wu Fuheng
Author-email: henry.woo@outlook.com
License: GPL
Keywords: sentosa,python
Platform: Independant
